requests_ss/__init__.py
requests_ss/requests_ss.py
html_content_scraper-0.1.0.dist-info/METADATA
html_content_scraper-0.1.0.dist-info/WHEEL
html_content_scraper-0.1.0.dist-info/entry_points.txt
html_content_scraper-0.1.0.dist-info/top_level.txt
html_content_scraper-0.1.0.dist-info/RECORD
